netter/__init__.py
netter/attribute.py
netter/cmds/__init__.py
netter/cmds/address.py
netter/cmds/domain.py
netter/utils/__init__.py
netter/utils/adapters.py
netter/utils/format.py
netter/utils/platform.py
netter/utils/prober.py
netter-0.1.dist-info/METADATA
netter-0.1.dist-info/WHEEL
netter-0.1.dist-info/entry_points.txt
netter-0.1.dist-info/top_level.txt
netter-0.1.dist-info/zip-safe
netter-0.1.dist-info/RECORD
